MANIFEST.in
README.rst
setup.cfg
setup.py
versioneer.py
scikit_surgerysurfacematch.egg-info/PKG-INFO
scikit_surgerysurfacematch.egg-info/SOURCES.txt
scikit_surgerysurfacematch.egg-info/dependency_links.txt
scikit_surgerysurfacematch.egg-info/entry_points.txt
scikit_surgerysurfacematch.egg-info/requires.txt
scikit_surgerysurfacematch.egg-info/top_level.txt
sksurgerysurfacematch/__init__.py
sksurgerysurfacematch/_version.py
sksurgerysurfacematch/algorithms/__init__.py
sksurgerysurfacematch/algorithms/goicp_registration.py
sksurgerysurfacematch/algorithms/pcl_icp_registration.py
sksurgerysurfacematch/algorithms/reconstructor_with_rectified_images.py
sksurgerysurfacematch/algorithms/sgbm_reconstructor.py
sksurgerysurfacematch/algorithms/stoyanov_reconstructor.py
sksurgerysurfacematch/algorithms/value_threshold_segmentor.py
sksurgerysurfacematch/interfaces/__init__.py
sksurgerysurfacematch/interfaces/rigid_registration.py
sksurgerysurfacematch/interfaces/stereo_reconstructor.py
sksurgerysurfacematch/interfaces/video_segmentor.py
sksurgerysurfacematch/pipelines/__init__.py
sksurgerysurfacematch/pipelines/register_cloud_to_stereo_mosaic.py
sksurgerysurfacematch/pipelines/register_cloud_to_stereo_reconstruction.py
sksurgerysurfacematch/ui/__init__.py
sksurgerysurfacematch/utils/__init__.py
sksurgerysurfacematch/utils/ply_utils.py
sksurgerysurfacematch/utils/projection_utils.py
sksurgerysurfacematch/utils/registration_utils.py